zendata/__init__.py
zendata/py.typed
zendata/api/__init__.py
zendata/api/health.py
zendata/core/__init__.py
zendata/core/batch.py
zendata/data/__init__.py
zendata/data/audio.py
zendata/data/base.py
zendata/data/images.py
zendata/data/files/__init__.py
zendata/data/files/audio.py
zendata/data/files/file.py
zendata/data/files/image.py
zendata/data/files/video.py
zendata/data/ml/__init__.py
zendata/data/ml/base.py
zendata/data/ml/classification.py
zendata/data/ml/embedding.py
zendata/data/ml/regression.py
zendata/data/ml/audio/__init__.py
zendata/data/ml/audio/classification.py
zendata/data/ml/audio/diarisation.py
zendata/data/ml/audio/segment.py
zendata/data/ml/audio/transcription.py
zendata/data/ml/computer_vision/__init__.py
zendata/data/ml/computer_vision/classification.py
zendata/data/ml/computer_vision/detection.py
zendata/data/ml/computer_vision/embedding.py
zendata/data/ml/generation/__init__.py
zendata/data/ml/generation/text.py
zendata/data/ml/nlp/__init__.py
zendata/data/ml/nlp/classification.py
zendata/data/ml/nlp/question_answer.py
zendata/data/text/__init__.py
zendata/data/text/text.py
zendata/data/vectors/__init__.py
zendata/data/vectors/tensor.py
zendata/ml/inputs/__init__.py
zendata/ml/inputs/audio.py
zendata/ml/inputs/base.py
zendata/ml/inputs/file.py
zendata/ml/inputs/image.py
zendata/ml/inputs/text.py
zendata/ml/inputs/video.py
zendata/ml/outputs/__init__.py
zendata/ml/outputs/base.py
zendata/ml/outputs/classification/labels.py
zendata/ml/outputs/classification/single_label.py
zendata/tasks/__init__.py
zendata/tasks/base.py
zendata/tasks/service.py
zendata/tasks/task.py
zendata-0.1.1.dist-info/METADATA
zendata-0.1.1.dist-info/WHEEL
zendata-0.1.1.dist-info/licenses/LICENSE
zendata-0.1.1.dist-info/RECORD
