Metadata-Version: 2.4
Name: zendata
Version: 0.1.1
Summary: Add your description here
Project-URL: Homepage, https://github.com/mitchou10/zendata
Project-URL: Issues, https://github.com/mitchou10/zendata/issues
Author-email: mitchou10 <misu.helal-ali@interieur.gouv.fr>
License-File: LICENSE
Requires-Python: >=3.13
Requires-Dist: pydantic>=2.11.4
